tests/__init__.py
tests/requirements.txt
tests/test_releases_meta.py
tests/test_utils.py
tests/test_versioned_instance.py
tests/__pycache__/__init__.cpython-37.pyc
tests/__pycache__/test_releases_meta.cpython-37.pyc
tests/__pycache__/test_utils.cpython-37.pyc
tests/__pycache__/test_versioned_instance.cpython-37.pyc
tests/releasesmeta/oem.yml
tests/releasesmeta/tdc.yml
tests/releasesmeta/tdc2ex.yml
tests/releasesmeta/tdc3ex.yml
tests/releasesmeta/versioned_instance.yml
verminator/__init__.py
verminator/config.py
verminator/releasemeta.py
verminator/utils.py
verminator/validate_release_dep.py
verminator/verminator.py
verminator/__pycache__/__init__.cpython-37.pyc
verminator/__pycache__/config.cpython-37.pyc
verminator/__pycache__/releasemeta.cpython-37.pyc
verminator/__pycache__/utils.cpython-37.pyc
verminator/__pycache__/verminator.cpython-37.pyc
verminator-1.3.3.4.data/scripts/verminator
verminator-1.3.3.4.dist-info/LICENSE
verminator-1.3.3.4.dist-info/METADATA
verminator-1.3.3.4.dist-info/WHEEL
verminator-1.3.3.4.dist-info/top_level.txt
verminator-1.3.3.4.dist-info/RECORD
