Metadata-Version: 2.1
Name: verminator
Version: 1.3.3.4
Summary: TDC image Version management tERMINATOR.
Home-page: http://github.com/WarpCloud/verminator
Author: Xiaming Chen
Author-email: xiaming.chen@transwarp.io
License: Transwarp
Keywords: utility,versioning
Platform: UNKNOWN
Classifier: Development Status :: 4 - Beta
Classifier: Environment :: Console
Classifier: Intended Audience :: Developers
Classifier: Operating System :: OS Independent
Classifier: Programming Language :: Python
Classifier: Programming Language :: Python :: 3.5
Classifier: Programming Language :: Python :: 3.6
Classifier: Programming Language :: Python :: 3.7
Classifier: Topic :: Software Development :: Libraries :: Python Modules
Requires-Dist: flex-version (<1.3.0,>=1.2.3)
Requires-Dist: pyyaml (>=4.2b1)
